odoo9_addon_web_decimal_numpad_dot-9.0.1.0.0-py2.7-nspkg.pth
odoo9_addon_web_decimal_numpad_dot-9.0.1.0.0.dist-info/DESCRIPTION.rst
odoo9_addon_web_decimal_numpad_dot-9.0.1.0.0.dist-info/METADATA
odoo9_addon_web_decimal_numpad_dot-9.0.1.0.0.dist-info/RECORD
odoo9_addon_web_decimal_numpad_dot-9.0.1.0.0.dist-info/WHEEL
odoo9_addon_web_decimal_numpad_dot-9.0.1.0.0.dist-info/metadata.json
odoo9_addon_web_decimal_numpad_dot-9.0.1.0.0.dist-info/namespace_packages.txt
odoo9_addon_web_decimal_numpad_dot-9.0.1.0.0.dist-info/top_level.txt
odoo_addons/web_decimal_numpad_dot/README.rst
odoo_addons/web_decimal_numpad_dot/__init__.py
odoo_addons/web_decimal_numpad_dot/__openerp__.py
odoo_addons/web_decimal_numpad_dot/static/description/icon.png
odoo_addons/web_decimal_numpad_dot/static/src/js/numpad_dot.js
odoo_addons/web_decimal_numpad_dot/views/web_decimal_numpad_dot.xml
